{"version":"3","services":{"x-ui":{"image":"enwaiax/x-ui","container_name":"x-ui","ports":["127.0.0.1:8050:54321","5100-5105:5100-5105/tcp","5100-5105:5100-5105/udp"],"tmpfs":["/tmp","/run","/run/lock"],"environment":{"TZ":"Asia/Shanghai"},"volumes":["/sys/fs/cgroup:/sys/fs/cgroup:ro","./x-ui/x-ui-data/:/etc/x-ui","./x-ui/ssl/:/root/cert/"],"restart":"always"},"nginx":{"container_name":"nginx","restart":"always","image":"nginx","network_mode":"host","environment":["TZ=Asia/Shanghai"],"volumes":["/data/devops/nginx/html:/etc/nginx/html","/data/devops/nginx/log:/var/log/nginx","/data/devops/nginx/conf/conf.d:/etc/nginx/conf.d","/data/devops/nginx/vhost:/etc/nginx/vhost","/data/devops/nginx/ssl:/etc/nginx/ssl","/data/devops/nginx/nginx.conf:/etc/nginx/nginx.conf:ro"],"ports":["80:80","443:443"]}}}